[
  { "slug": "actor-tom-hanks",           "name": "Tom Hanks",          "tier": "standard", "wikipedia": "Tom_Hanks",           "attributes": { "gender": "male",   "hair_color": "gray",   "hair_length": "short",  "age_group": "senior",      "nationality": "American",   "facial_hair": false, "glasses": false } },
  { "slug": "actor-meryl-streep",        "name": "Meryl Streep",       "tier": "standard", "wikipedia": "Meryl_Streep",        "attributes": { "gender": "female", "hair_color": "blonde", "hair_length": "medium", "age_group": "senior",      "nationality": "American",   "facial_hair": false, "glasses": false } },
  { "slug": "actor-denzel-washington",   "name": "Denzel Washington",  "tier": "standard", "wikipedia": "Denzel_Washington",   "attributes": { "gender": "male",   "hair_color": "gray",   "hair_length": "short",  "age_group": "senior",      "nationality": "American",   "facial_hair": false, "glasses": false } },
  { "slug": "actor-cate-blanchett",      "name": "Cate Blanchett",     "tier": "standard", "wikipedia": "Cate_Blanchett",      "attributes": { "gender": "female", "hair_color": "blonde", "hair_length": "medium", "age_group": "middle-aged", "nationality": "Australian", "facial_hair": false, "glasses": false } },
  { "slug": "actor-morgan-freeman",      "name": "Morgan Freeman",     "tier": "standard", "wikipedia": "Morgan_Freeman",      "attributes": { "gender": "male",   "hair_color": "gray",   "hair_length": "short",  "age_group": "senior",      "nationality": "American",   "facial_hair": false, "glasses": false } },
  { "slug": "actor-scarlett-johansson",  "name": "Scarlett Johansson", "tier": "standard", "wikipedia": "Scarlett_Johansson",  "attributes": { "gender": "female", "hair_color": "blonde", "hair_length": "medium", "age_group": "middle-aged", "nationality": "American",   "facial_hair": false, "glasses": false } },
  { "slug": "actor-leonardo-dicaprio",   "name": "Leonardo DiCaprio",  "tier": "standard", "wikipedia": "Leonardo_DiCaprio",   "attributes": { "gender": "male",   "hair_color": "brown",  "hair_length": "medium", "age_group": "middle-aged", "nationality": "American",   "facial_hair": true,  "glasses": false } },
  { "slug": "actor-jennifer-lawrence",   "name": "Jennifer Lawrence",  "tier": "standard", "wikipedia": "Jennifer_Lawrence",   "attributes": { "gender": "female", "hair_color": "blonde", "hair_length": "medium", "age_group": "young",       "nationality": "American",   "facial_hair": false, "glasses": false } },
  { "slug": "actor-viola-davis",         "name": "Viola Davis",        "tier": "standard", "wikipedia": "Viola_Davis",         "attributes": { "gender": "female", "hair_color": "black",  "hair_length": "short",  "age_group": "middle-aged", "nationality": "American",   "facial_hair": false, "glasses": false } },
  { "slug": "actor-dwayne-johnson",      "name": "Dwayne Johnson",     "tier": "standard", "wikipedia": "Dwayne_Johnson",      "attributes": { "gender": "male",   "hair_color": "black",  "hair_length": "bald",   "age_group": "middle-aged", "nationality": "American",   "facial_hair": false, "glasses": false } },
  { "slug": "actor-natalie-portman",     "name": "Natalie Portman",    "tier": "standard", "wikipedia": "Natalie_Portman",     "attributes": { "gender": "female", "hair_color": "brown",  "hair_length": "medium", "age_group": "middle-aged", "nationality": "Israeli",    "facial_hair": false, "glasses": false } },
  { "slug": "actor-robert-downey-jr",    "name": "Robert Downey Jr.",  "tier": "standard", "wikipedia": "Robert_Downey_Jr.",   "attributes": { "gender": "male",   "hair_color": "brown",  "hair_length": "short",  "age_group": "middle-aged", "nationality": "American",   "facial_hair": true,  "glasses": false } },
  { "slug": "actor-halle-berry",         "name": "Halle Berry",        "tier": "standard", "wikipedia": "Halle_Berry",         "attributes": { "gender": "female", "hair_color": "brown",  "hair_length": "short",  "age_group": "middle-aged", "nationality": "American",   "facial_hair": false, "glasses": false } },
  { "slug": "actor-will-smith",          "name": "Will Smith",         "tier": "standard", "wikipedia": "Will_Smith",          "attributes": { "gender": "male",   "hair_color": "black",  "hair_length": "short",  "age_group": "middle-aged", "nationality": "American",   "facial_hair": false, "glasses": false } },
  { "slug": "actor-emma-stone",          "name": "Emma Stone",         "tier": "standard", "wikipedia": "Emma_Stone",          "attributes": { "gender": "female", "hair_color": "red",    "hair_length": "medium", "age_group": "young",       "nationality": "American",   "facial_hair": false, "glasses": false } },
  { "slug": "actor-ryan-reynolds",       "name": "Ryan Reynolds",      "tier": "standard", "wikipedia": "Ryan_Reynolds",       "attributes": { "gender": "male",   "hair_color": "brown",  "hair_length": "short",  "age_group": "middle-aged", "nationality": "Canadian",   "facial_hair": false, "glasses": false } },
  { "slug": "actor-sandra-bullock",      "name": "Sandra Bullock",     "tier": "standard", "wikipedia": "Sandra_Bullock",      "attributes": { "gender": "female", "hair_color": "brown",  "hair_length": "medium", "age_group": "middle-aged", "nationality": "American",   "facial_hair": false, "glasses": false } },
  { "slug": "actor-chris-pratt",         "name": "Chris Pratt",        "tier": "standard", "wikipedia": "Chris_Pratt",         "attributes": { "gender": "male",   "hair_color": "brown",  "hair_length": "short",  "age_group": "middle-aged", "nationality": "American",   "facial_hair": false, "glasses": false } },
  { "slug": "actor-angelina-jolie",      "name": "Angelina Jolie",     "tier": "standard", "wikipedia": "Angelina_Jolie",      "attributes": { "gender": "female", "hair_color": "brown",  "hair_length": "long",   "age_group": "middle-aged", "nationality": "American",   "facial_hair": false, "glasses": false } },
  { "slug": "actor-brad-pitt",           "name": "Brad Pitt",          "tier": "standard", "wikipedia": "Brad_Pitt",           "attributes": { "gender": "male",   "hair_color": "blonde", "hair_length": "medium", "age_group": "senior",      "nationality": "American",   "facial_hair": true,  "glasses": false } },
  { "slug": "actor-idris-elba",          "name": "Idris Elba",         "tier": "extended", "wikipedia": "Idris_Elba",          "attributes": { "gender": "male",   "hair_color": "black",  "hair_length": "short",  "age_group": "middle-aged", "nationality": "British",    "facial_hair": true,  "glasses": false } },
  { "slug": "actor-chadwick-boseman",    "name": "Chadwick Boseman",   "tier": "extended", "wikipedia": "Chadwick_Boseman",    "attributes": { "gender": "male",   "hair_color": "black",  "hair_length": "short",  "age_group": "middle-aged", "nationality": "American",   "facial_hair": false, "glasses": false } },
  { "slug": "actor-zendaya",             "name": "Zendaya",            "tier": "extended", "wikipedia": "Zendaya",             "attributes": { "gender": "female", "hair_color": "brown",  "hair_length": "long",   "age_group": "young",       "nationality": "American",   "facial_hair": false, "glasses": false } },
  { "slug": "actor-timothee-chalamet",   "name": "Timothée Chalamet",  "tier": "extended", "wikipedia": "Timoth%C3%A9e_Chalamet", "attributes": { "gender": "male", "hair_color": "brown", "hair_length": "medium", "age_group": "young",       "nationality": "French",     "facial_hair": false, "glasses": false } }
]
